mac_print/99-pico.rules
mac_print/install-udev-rules.sh
mac_print/picosend.py
usb_remote/__init__.py
usb_remote/__main__.py
usb_remote/_version.py
usb_remote/api.py
usb_remote/client.py
usb_remote/client_api.py
usb_remote/client_service.py
usb_remote/config.py
usb_remote/port.py
usb_remote/server.py
usb_remote/service.py
usb_remote/usbdevice.py
usb_remote/utility.py
usb_remote-2.3.2.dist-info/licenses/LICENSE
usb_remote-2.3.2.dist-info/METADATA
usb_remote-2.3.2.dist-info/WHEEL
usb_remote-2.3.2.dist-info/entry_points.txt
usb_remote-2.3.2.dist-info/top_level.txt
usb_remote-2.3.2.dist-info/RECORD
