Metadata-Version: 2.4
Name: usb-remote
Version: 2.3.2
Summary: A client-server application for remotely sharing USB devices with usbip
Author-email: Giles Knap <giles.knap@diamond.ac.uk>
License:                                  Apache License
Project-URL: GitHub, https://github.com/epics-containers/usb-remote
Classifier: Development Status :: 3 - Alpha
Classifier: License :: OSI Approved :: Apache Software License
Classifier: Programming Language :: Python :: 3.11
Classifier: Programming Language :: Python :: 3.12
Classifier: Programming Language :: Python :: 3.13
Requires-Python: >=3.11
License-File: LICENSE
Requires-Dist: pydantic>=2.0.0
Requires-Dist: pyserial>=3.5
Requires-Dist: pyudev>=0.24.4
Requires-Dist: pyusb>=1.3.1
Requires-Dist: pyyaml>=6.0.0
Requires-Dist: typer>=0.20.0
Dynamic: license-file
